{
  "marketing_stripe": {
    "text": "Quer comprar no VAREJO? Clique aqui!",
    "link": "https://jessimake.com/",
    "background": "#fc2792",
    "color": "#ffffff"
  },
  "contacts_stripe": {
    "pages": [],
    "phone_wpp": true,
    "socials": true
  },
  "categories_list": {
    "featured": [
      "/box-e-kit-de-maquiagens-no-atacado?ALTO ATACADO",
      "/atacadinho-unidade?ATACADO",
      "/kits-revenda?KITS REVENDA",
      "/dia-do-cliente?DIA DO CLIENTE",
      "/marcas?MARCAS",
      "/maquiagem?MAQUIAGEM",
      "/acessorios-para-maquiagem?ACESSÓRIOS",
      "/eletronico?ELETRÔNICOS",
      "/linha-facial-skincare?SKINCARE",
      "/novidades?NOVIDADES",
      "/outras?OUTRAS"
    ],
    "random": 0,
    "full_width": true
  },
  "search_input": true,
  "desktop_megamenu": false,
  "alphabetical_order_submenu": true,
  "full_width_submenu": true
}